sensorpush/__init__.py
sensorpush/demo.py
sensorpush/sensorpush.py
sensorpush/sensorpush_parser.py
sensorpush/test.py
sensorpush/utils.py
sensorpush_bleak-1.0.7.dist-info/LICENSE
sensorpush_bleak-1.0.7.dist-info/METADATA
sensorpush_bleak-1.0.7.dist-info/WHEEL
sensorpush_bleak-1.0.7.dist-info/top_level.txt
sensorpush_bleak-1.0.7.dist-info/RECORD
