Metadata-Version: 2.1
Name: sensorpush-bleak
Version: 1.0.7
Summary: library to read from Sensorpush HW.t bluetooth sensor
Author-email: Ed McGrath <edward@edwardmcgrath.com>
License: Copyright (c) 2021 Edward McGrath and others
Keywords: sensorpush,HW.t,temperature,sensor,bluetooth,ble
Classifier: License :: OSI Approved :: MIT License
Classifier: Programming Language :: Python
Classifier: Programming Language :: Python :: 3
Requires-Python: >=3.9
License-File: LICENSE
Requires-Dist: bleak (>=0.19.5)
Requires-Dist: pytz (>=2022.2.1)
